[
    {
        "title": "BBS",
        "icon": "lucide:folder",
        "items": [
            {
                "name": "NodeSeek",
                "avatar": "https://pic.000.moe/pic/696c80ecb9379.png",
                "description": "Nodeseek is a place for people who love web development, hosting, vps / server and other geek things.",
                "url": "https://nodeseek.com",
                "category": "BBS",
                "id": "NodeSeek",
                "badge": "MJJ",
                "badgeColor": "success"
            },
            {
                "name": "LinuxDo",
                "avatar": "https://pic.000.moe/pic/696c80ecdf320.png",
                "description": "真诚、友善、团结、专业，共建你我引以为荣之社区。",
                "url": "https://linux.do",
                "category": "BBS",
                "id": "LinuxDo",
                "badge": "佬友",
                "badgeColor": "success"
            }
        ]
    }
]